{
  "_format": "hh-sol-cache-2",
  "files": {
    "/home/debielily/Desktop/Web3bridge-Web3-Cohort-XIII/onsite-program/submissions/week-6/day-1/Deborah_Olaboye/contracts/FactorySavings.sol": {
      "lastModificationDate": 1754920661335,
      "contentHash": "450e7cc7a1c0a8dd60d9e7b2f999fa70",
      "sourceName": "contracts/FactorySavings.sol",
      "solcConfig": {
        "version": "0.8.28",
        "settings": {
          "evmVersion": "paris",
          "optimizer": {
            "enabled": false,
            "runs": 200
          },
          "outputSelection": {
            "*": {
              "*": [
                "abi",
                "evm.bytecode",
                "evm.deployedBytecode",
                "evm.methodIdentifiers",
                "metadata"
              ],
              "": [
                "ast"
              ]
            }
          },
          "metadata": {
            "useLiteralContent": false
          }
        }
      },
      "imports": [
        "@openzeppelin/contracts/token/ERC20/IERC20.sol",
        "../interfaces/IPiggyBank.sol",
        "./PiggyBank.sol"
      ],
      "versionPragmas": [
        "^0.8.26"
      ],
      "artifacts": [
        "FactorySavings"
      ]
    },
    "/home/debielily/Desktop/Web3bridge-Web3-Cohort-XIII/onsite-program/submissions/week-6/day-1/Deborah_Olaboye/contracts/PiggyBank.sol": {
      "lastModificationDate": 1754923052946,
      "contentHash": "a52d0e1aac087b0d526db1914d27c22b",
      "sourceName": "contracts/PiggyBank.sol",
      "solcConfig": {
        "version": "0.8.28",
        "settings": {
          "evmVersion": "paris",
          "optimizer": {
            "enabled": false,
            "runs": 200
          },
          "outputSelection": {
            "*": {
              "*": [
                "abi",
                "evm.bytecode",
                "evm.deployedBytecode",
                "evm.methodIdentifiers",
                "metadata"
              ],
              "": [
                "ast"
              ]
            }
          },
          "metadata": {
            "useLiteralContent": false
          }
        }
      },
      "imports": [
        "@openzeppelin/contracts/token/ERC20/IERC20.sol",
        "../interfaces/IPiggyBank.sol"
      ],
      "versionPragmas": [
        "^0.8.26"
      ],
      "artifacts": [
        "PiggyBank"
      ]
    },
    "/home/debielily/Desktop/Web3bridge-Web3-Cohort-XIII/onsite-program/submissions/week-6/day-1/Deborah_Olaboye/interfaces/IPiggyBank.sol": {
      "lastModificationDate": 1754919411590,
      "contentHash": "ba13fecd0d07166dd59aafb3d2706b24",
      "sourceName": "interfaces/IPiggyBank.sol",
      "solcConfig": {
        "version": "0.8.28",
        "settings": {
          "evmVersion": "paris",
          "optimizer": {
            "enabled": false,
            "runs": 200
          },
          "outputSelection": {
            "*": {
              "*": [
                "abi",
                "evm.bytecode",
                "evm.deployedBytecode",
                "evm.methodIdentifiers",
                "metadata"
              ],
              "": [
                "ast"
              ]
            }
          },
          "metadata": {
            "useLiteralContent": false
          }
        }
      },
      "imports": [],
      "versionPragmas": [
        "^0.8.26"
      ],
      "artifacts": [
        "IPiggyBank"
      ]
    },
    "/home/debielily/Desktop/Web3bridge-Web3-Cohort-XIII/onsite-program/submissions/week-6/day-1/Deborah_Olaboye/node_modules/@openzeppelin/contracts/token/ERC20/IERC20.sol": {
      "lastModificationDate": 1754915075740,
      "contentHash": "9261adf6457863de3e9892f51317ec89",
      "sourceName": "@openzeppelin/contracts/token/ERC20/IERC20.sol",
      "solcConfig": {
        "version": "0.8.28",
        "settings": {
          "evmVersion": "paris",
          "optimizer": {
            "enabled": false,
            "runs": 200
          },
          "outputSelection": {
            "*": {
              "*": [
                "abi",
                "evm.bytecode",
                "evm.deployedBytecode",
                "evm.methodIdentifiers",
                "metadata"
              ],
              "": [
                "ast"
              ]
            }
          },
          "metadata": {
            "useLiteralContent": false
          }
        }
      },
      "imports": [],
      "versionPragmas": [
        ">=0.4.16"
      ],
      "artifacts": [
        "IERC20"
      ]
    },
    "/home/debielily/Desktop/Web3bridge-Web3-Cohort-XIII/onsite-program/submissions/week-6/day-1/Deborah_Olaboye/node_modules/@openzeppelin/contracts/token/ERC20/extensions/IERC20Metadata.sol": {
      "lastModificationDate": 1754915075740,
      "contentHash": "513778b30d2750f5d2b9b19bbcf748a5",
      "sourceName": "@openzeppelin/contracts/token/ERC20/extensions/IERC20Metadata.sol",
      "solcConfig": {
        "version": "0.8.28",
        "settings": {
          "evmVersion": "paris",
          "optimizer": {
            "enabled": false,
            "runs": 200
          },
          "outputSelection": {
            "*": {
              "*": [
                "abi",
                "evm.bytecode",
                "evm.deployedBytecode",
                "evm.methodIdentifiers",
                "metadata"
              ],
              "": [
                "ast"
              ]
            }
          },
          "metadata": {
            "useLiteralContent": false
          }
        }
      },
      "imports": [
        "../IERC20.sol"
      ],
      "versionPragmas": [
        ">=0.6.2"
      ],
      "artifacts": [
        "IERC20Metadata"
      ]
    },
    "/home/debielily/Desktop/Web3bridge-Web3-Cohort-XIII/onsite-program/submissions/week-6/day-1/Deborah_Olaboye/node_modules/@openzeppelin/contracts/token/ERC20/ERC20.sol": {
      "lastModificationDate": 1754915075727,
      "contentHash": "59dfce11284f2636db261df9b6a18f81",
      "sourceName": "@openzeppelin/contracts/token/ERC20/ERC20.sol",
      "solcConfig": {
        "version": "0.8.28",
        "settings": {
          "evmVersion": "paris",
          "optimizer": {
            "enabled": false,
            "runs": 200
          },
          "outputSelection": {
            "*": {
              "*": [
                "abi",
                "evm.bytecode",
                "evm.deployedBytecode",
                "evm.methodIdentifiers",
                "metadata"
              ],
              "": [
                "ast"
              ]
            }
          },
          "metadata": {
            "useLiteralContent": false
          }
        }
      },
      "imports": [
        "./IERC20.sol",
        "./extensions/IERC20Metadata.sol",
        "../../utils/Context.sol",
        "../../interfaces/draft-IERC6093.sol"
      ],
      "versionPragmas": [
        "^0.8.20"
      ],
      "artifacts": [
        "ERC20"
      ]
    },
    "/home/debielily/Desktop/Web3bridge-Web3-Cohort-XIII/onsite-program/submissions/week-6/day-1/Deborah_Olaboye/node_modules/@openzeppelin/contracts/utils/Context.sol": {
      "lastModificationDate": 1754915075712,
      "contentHash": "67bfbc07588eb8683b3fd8f6f909563e",
      "sourceName": "@openzeppelin/contracts/utils/Context.sol",
      "solcConfig": {
        "version": "0.8.28",
        "settings": {
          "evmVersion": "paris",
          "optimizer": {
            "enabled": false,
            "runs": 200
          },
          "outputSelection": {
            "*": {
              "*": [
                "abi",
                "evm.bytecode",
                "evm.deployedBytecode",
                "evm.methodIdentifiers",
                "metadata"
              ],
              "": [
                "ast"
              ]
            }
          },
          "metadata": {
            "useLiteralContent": false
          }
        }
      },
      "imports": [],
      "versionPragmas": [
        "^0.8.20"
      ],
      "artifacts": [
        "Context"
      ]
    },
    "/home/debielily/Desktop/Web3bridge-Web3-Cohort-XIII/onsite-program/submissions/week-6/day-1/Deborah_Olaboye/node_modules/@openzeppelin/contracts/interfaces/draft-IERC6093.sol": {
      "lastModificationDate": 1754915075721,
      "contentHash": "5041977bbe908de2e6ed0270447f79ad",
      "sourceName": "@openzeppelin/contracts/interfaces/draft-IERC6093.sol",
      "solcConfig": {
        "version": "0.8.28",
        "settings": {
          "evmVersion": "paris",
          "optimizer": {
            "enabled": false,
            "runs": 200
          },
          "outputSelection": {
            "*": {
              "*": [
                "abi",
                "evm.bytecode",
                "evm.deployedBytecode",
                "evm.methodIdentifiers",
                "metadata"
              ],
              "": [
                "ast"
              ]
            }
          },
          "metadata": {
            "useLiteralContent": false
          }
        }
      },
      "imports": [],
      "versionPragmas": [
        ">=0.8.4"
      ],
      "artifacts": [
        "IERC1155Errors",
        "IERC20Errors",
        "IERC721Errors"
      ]
    },
    "/home/debielily/Desktop/Web3bridge-Web3-Cohort-XIII/onsite-program/submissions/week-6/day-1/Deborah_Olaboye/contracts/Token.sol": {
      "lastModificationDate": 1754922451568,
      "contentHash": "7cba7b488ba050a9746016aad292fe8f",
      "sourceName": "contracts/Token.sol",
      "solcConfig": {
        "version": "0.8.28",
        "settings": {
          "evmVersion": "paris",
          "optimizer": {
            "enabled": false,
            "runs": 200
          },
          "outputSelection": {
            "*": {
              "*": [
                "abi",
                "evm.bytecode",
                "evm.deployedBytecode",
                "evm.methodIdentifiers",
                "metadata"
              ],
              "": [
                "ast"
              ]
            }
          },
          "metadata": {
            "useLiteralContent": false
          }
        }
      },
      "imports": [
        "@openzeppelin/contracts/token/ERC20/ERC20.sol"
      ],
      "versionPragmas": [
        "^0.8.26"
      ],
      "artifacts": [
        "TokenT"
      ]
    }
  }
}
